<?xml version="1.0" encoding="UTF-8"?>
<!DOCTYPE mapper PUBLIC "-//mybatis.org//DTD Mapper 3.0//EN" "http://mybatis.org/dtd/mybatis-3-mapper.dtd">
<mapper namespace="vu.lt.mybatis.dao.BuildingMapper">
  <resultMap id="BaseResultMap" type="vu.lt.mybatis.model.Building">
    <!--
      WARNING - @mbg.generated
      This element is automatically generated by MyBatis Generator, do not modify.
      This element was generated on Mon Apr 26 23:33:23 EEST 2021.
    -->
    <id column="ID" jdbcType="INTEGER" property="id" />
    <result column="ADDRESS" jdbcType="VARCHAR" property="address" />
    <result column="BUILD_YEAR" jdbcType="INTEGER" property="buildYear" />
    <result column="MANUFACTURER_ID" jdbcType="INTEGER" property="manufacturerId" />
    <association property="manufacturer" javaType="vu.lt.mybatis.model.Manufacturer">
      <id property="id" column="ID"/>
      <result property="name" column="NAME"/>
    </association>
  </resultMap>
  <delete id="deleteByPrimaryKey" parameterType="java.lang.Integer">
    <!--
      WARNING - @mbg.generated
      This element is automatically generated by MyBatis Generator, do not modify.
      This element was generated on Mon Apr 26 23:33:23 EEST 2021.
    -->
    delete from PUBLIC.BUILDING
    where ID = #{id,jdbcType=INTEGER}
  </delete>
  <insert id="insert" keyColumn="ID" keyProperty="id" parameterType="vu.lt.mybatis.model.Building" useGeneratedKeys="true">
    <!--
      WARNING - @mbg.generated
      This element is automatically generated by MyBatis Generator, do not modify.
      This element was generated on Mon Apr 26 23:33:23 EEST 2021.
    -->
    insert into PUBLIC.BUILDING (ADDRESS, BUILD_YEAR, MANUFACTURER_ID
      )
    values (#{address,jdbcType=VARCHAR}, #{buildYear,jdbcType=INTEGER}, #{manufacturerId,jdbcType=INTEGER}
      )
  </insert>
  <update id="updateByPrimaryKey" parameterType="vu.lt.mybatis.model.Building">
    <!--
      WARNING - @mbg.generated
      This element is automatically generated by MyBatis Generator, do not modify.
      This element was generated on Mon Apr 26 23:33:23 EEST 2021.
    -->
    update PUBLIC.BUILDING
    set ADDRESS = #{address,jdbcType=VARCHAR},
      BUILD_YEAR = #{buildYear,jdbcType=INTEGER},
      MANUFACTURER_ID = #{manufacturerId,jdbcType=INTEGER}
    where ID = #{id,jdbcType=INTEGER}
  </update>
  <select id="selectByPrimaryKey" parameterType="java.lang.Integer" resultMap="BaseResultMap">
    <!--
      WARNING - @mbg.generated
      This element is automatically generated by MyBatis Generator, do not modify.
      This element was generated on Mon Apr 26 23:33:23 EEST 2021.
    -->
    select ID, ADDRESS, BUILD_YEAR, MANUFACTURER_ID
    from PUBLIC.BUILDING
    where ID = #{id,jdbcType=INTEGER}
  </select>
  <select id="selectAll" resultMap="BaseResultMap">
    <!--
      WARNING - @mbg.generated
      This element is automatically generated by MyBatis Generator, do not modify.
      This element was generated on Mon Apr 26 23:33:23 EEST 2021.
    -->
    select ID, ADDRESS, BUILD_YEAR, MANUFACTURER_ID
    from PUBLIC.BUILDING
  </select>
  <select id="selectManufacturerBuildings" parameterType="java.lang.Integer" resultMap="BaseResultMap">
    select BUILDING.* from PUBLIC.BUILDING where BUILDING.MANUFACTURER_ID = #{manufacturerId, jdbcType=INTEGER}
  </select>
</mapper>
